pylich/__init__.py
pylich/checker.py
pylich/cli.py
pylich-0.4.0.dist-info/LICENSE
pylich-0.4.0.dist-info/METADATA
pylich-0.4.0.dist-info/WHEEL
pylich-0.4.0.dist-info/entry_points.txt
pylich-0.4.0.dist-info/RECORD
